decli/__init__.py
decli/application.py
decli/py.typed
decli-0.6.0.dist-info/LICENSE
decli-0.6.0.dist-info/METADATA
decli-0.6.0.dist-info/WHEEL
decli-0.6.0.dist-info/RECORD
