Metadata-Version: 2.1
Name: decli
Version: 0.6.0
Summary: Minimal, easy-to-use, declarative cli tool
License: MIT
Author: Santiago Fraire
Author-email: santiwilly@gmail.com
Requires-Python: >=3.7
Classifier: License :: OSI Approved :: MIT License
Classifier: Programming Language :: Python :: 3
Classifier: Programming Language :: Python :: 3.7
Classifier: Programming Language :: Python :: 3.8
Classifier: Programming Language :: Python :: 3.9
Classifier: Programming Language :: Python :: 3.10
Classifier: Programming Language :: Python :: 3.11
